ipysim/__init__.py
ipysim/core.py
ipysim/params.py
ipysim/plotting.py
ipysim/simulation_ui.py
ipysim/utils.py
ipysim/simulations/__init__.py
ipysim/simulations/simulate_flip_magnet.py
ipysim/simulations/simulate_maglev.py
ipysim/simulations/simulate_maglev_with_noise.py
ipysim-1.0.1.dist-info/METADATA
ipysim-1.0.1.dist-info/WHEEL
ipysim-1.0.1.dist-info/RECORD
